pytest_trialtemp/__init__.py
pytest_trialtemp/trialtemp.py
pytest_trialtemp-1.0.1.dist-info/DESCRIPTION.rst
pytest_trialtemp-1.0.1.dist-info/entry_points.txt
pytest_trialtemp-1.0.1.dist-info/METADATA
pytest_trialtemp-1.0.1.dist-info/metadata.json
pytest_trialtemp-1.0.1.dist-info/RECORD
pytest_trialtemp-1.0.1.dist-info/top_level.txt
pytest_trialtemp-1.0.1.dist-info/WHEEL
