Metadata-Version: 2.0
Name: pytest-trialtemp
Version: 1.0.1
Summary: py.test plugin for using the same _trial_temp working directory as trial
Home-page: http://github.com/jerith/pytest-trialtemp
Author: Jeremy Thurgood
Author-email: firxen@gmail.com
License: MIT
Platform: UNKNOWN
Requires-Dist: pytest
Requires-Dist: Twisted
